ftps/__init__.py
ftps/ftps.py
ftps-0.1.0.dist-info/DESCRIPTION.rst
ftps-0.1.0.dist-info/METADATA
ftps-0.1.0.dist-info/RECORD
ftps-0.1.0.dist-info/WHEEL
ftps-0.1.0.dist-info/metadata.json
ftps-0.1.0.dist-info/top_level.txt
