Metadata-Version: 2.0
Name: ftps
Version: 0.1.0
Summary: ftps client based on pycurl
Home-page: https://github.com/jcollado/ftps
Author: Javier Collado
Author-email: javier.collado@gmail.com
License: MIT license
Keywords: ftps
Platform: UNKNOWN
Classifier: Development Status :: 2 - Pre-Alpha
Classifier: Intended Audience :: Developers
Classifier: License :: OSI Approved :: MIT License
Classifier: Natural Language :: English
Classifier: Programming Language :: Python :: 2
Classifier: Programming Language :: Python :: 2.7
Classifier: Programming Language :: Python :: 3
Classifier: Programming Language :: Python :: 3.5
Requires-Dist: pycurl
Requires-Dist: six
